cli/__init__.py
cli/admin.py
cli/experiment.py
cli/main.py
cli/object_to_markdown.py
cli/pretty.py
cli/project.py
qcogclient/__init__.py
qcogclient/_version.py
qcogclient/httpclient.py
qcogclient/logger.py
qcogclient/store.py
qcogclient/utils.py
qcogclient/qcog/_file.py
qcogclient/qcog/_initializer.py
qcogclient/qcog/adapters.py
qcogclient/qcog/admin.py
qcogclient/qcog/errors.py
qcogclient/qcog/events.py
qcogclient/qcog/experiment.py
qcogclient/qcog/project.py
qcogclient/qcog/typ.py
qcogclient-0.0.33.dist-info/METADATA
qcogclient-0.0.33.dist-info/WHEEL
qcogclient-0.0.33.dist-info/entry_points.txt
qcogclient-0.0.33.dist-info/top_level.txt
qcogclient-0.0.33.dist-info/RECORD
