Metadata-Version: 2.4
Name: qcogclient
Version: 0.0.33
Author: Qognitive
Classifier: Programming Language :: Python :: 3
Requires-Python: >=3.12
Requires-Dist: aiohttp>=3.11.18
Requires-Dist: colorama>=0.4.6
Requires-Dist: mypy>=1.15.0
Requires-Dist: pydantic-settings>=2.9.1
Requires-Dist: returns>=0.25.0
Requires-Dist: rich>=14.0.0
Requires-Dist: sentry-sdk>=2.32.0
Requires-Dist: termcolor>=3.0.1
Requires-Dist: tqdm>=4.67.1
